Android_tcpdump_tool/Android_tcpdump.py
Android_tcpdump_tool/__init__.py
android_tcpdump_tool-1.0.1.dist-info/METADATA
android_tcpdump_tool-1.0.1.dist-info/WHEEL
android_tcpdump_tool-1.0.1.dist-info/entry_points.txt
android_tcpdump_tool-1.0.1.dist-info/top_level.txt
android_tcpdump_tool-1.0.1.dist-info/RECORD
