Metadata-Version: 2.4
Name: Android_tcpdump-tool
Version: 1.0.1
Summary: A command-line tool for capturing Android app traffic using tcpdump.
Home-page: https://github.com/idontknowoman/Android_tcpdump_tool
Author: Dubai
Author-email: fjing2022@whu.edu.cn
Classifier: Programming Language :: Python :: 3
Classifier: License :: OSI Approved :: MIT License
Classifier: Operating System :: OS Independent
Requires-Python: >=3.6
Dynamic: author
Dynamic: author-email
Dynamic: classifier
Dynamic: description
Dynamic: description-content-type
Dynamic: home-page
Dynamic: requires-python
Dynamic: summary
